{
  "Moves": {
    "Level": {
      "10": [
        "Screech",
        "Agility",
        "Double Hit"
      ],
      "14": [
        "Fling",
        "Nasty Plot"
      ],
      "18": [
        "Last Resort"
      ]
    },
    "Starting Moves": [
      "Astonish",
      "Dual Chop",
      "Sand Attack",
      "Scratch",
      "Tail Whip",
      "Baton Pass",
      "Tickle",
      "Fury Swipes",
      "Swift"
    ],
    "TM": [
      1,
      6,
      10,
      11,
      12,
      15,
      17,
      18,
      21,
      22,
      24,
      25,
      27,
      30,
      31,
      32,
      40,
      42,
      44,
      45,
      46,
      47,
      48,
      56,
      62,
      65,
      66,
      68,
      73,
      85,
      86,
      87,
      88,
      89,
      90,
      100
    ]
  },
  "index": 424,
  "Abilities": [
    "Technician",
    "Pickup"
  ],
  "Type": [
    "Normal"
  ],
  "SR": 11.0,
  "AC": 15,
  "Hit Dice": 10,
  "HP": 94,
  "WSp": 40,
  "attributes": {
    "STR": 15,
    "DEX": 19,
    "CON": 16,
    "INT": 6,
    "WIS": 12,
    "CHA": 10
  },
  "MIN LVL FD": 8,
  "saving_throws": [
    "DEX"
  ],
  "Skill": [
    "Acrobatics",
    "Sleight of Hand"
  ],
  "Hidden Ability": "Skill Link",
  "Climbing Speed": 40
}