{
  "AC": 17,
  "Abilities": [
    "Water Bubble"
  ],
  "HP": 60,
  "Hidden Ability": "Water Absorb",
  "Hit Dice": 10,
  "MIN LVL FD": 5,
  "Moves": {
    "Level": {
      "10": [
        "Aqua Ring"
      ],
      "14": [
        "Leech Life",
        "Crunch"
      ],
      "18": [
        "Lunge",
        "Mirror Coat",
        "Liquidation",
        "Entrainment"
      ],
      "6": [
        "Bubble Beam",
        "Bite"
      ]
    },
    "Starting Moves": [
      "Bubble",
      "Bug Bite",
      "Infestation",
      "Soak",
      "Spider Web",
      "Wide Guard"
    ],
    "TM": [
      6,
      10,
      13,
      14,
      17,
      18,
      21,
      27,
      28,
      32,
      42,
      44,
      45,
      48,
      55,
      79,
      81,
      83,
      84,
      87,
      88,
      90,
      94,
      98,
      100
    ]
  },
  "SR": 10.0,
  "Skill": [
    "Sleight of Hand"
  ],
  "Ssp": 30,
  "Type": [
    "Water",
    "Bug"
  ],
  "WSp": 25,
  "attributes": {
    "CHA": 10,
    "CON": 18,
    "DEX": 15,
    "INT": 6,
    "STR": 15,
    "WIS": 12
  },
  "index": 752,
  "saving_throws": [
    "Dexterity"
  ],
  "size": "Large"
}