{
  "Moves": {
    "Level": {
      "18": [
        "Aqua Tail",
        "Dragon Rush",
        "Safeguard",
        "Dragon Dance",
        "Outrage",
        "Hyper Beam",
        "Hurricane"
      ]
    },
    "Starting Moves": [
      "Fire Punch",
      "Leer",
      "Roost",
      "Thunder Punch",
      "Wing Attack",
      "Wrap",
      "Thunder Wave",
      "Twister",
      "Dragon Rage",
      "Slam",
      "Agility",
      "Dragon Tail"
    ],
    "TM": [
      2,
      5,
      6,
      7,
      10,
      11,
      13,
      14,
      15,
      16,
      17,
      18,
      19,
      20,
      21,
      24,
      25,
      26,
      27,
      31,
      32,
      35,
      37,
      38,
      39,
      40,
      42,
      44,
      45,
      48,
      51,
      52,
      56,
      58,
      59,
      68,
      71,
      73,
      76,
      78,
      80,
      82,
      87,
      88,
      90,
      94,
      98,
      100
    ]
  },
  "index": 149,
  "Abilities": [
    "Inner Focus"
  ],
  "Type": [
    "Dragon",
    "Flying"
  ],
  "SR": 14.0,
  "AC": 17,
  "Hit Dice": 12,
  "HP": 173,
  "WSp": 30,
  "Fsp": 50,
  "attributes": {
    "STR": 19,
    "DEX": 18,
    "CON": 16,
    "INT": 6,
    "WIS": 14,
    "CHA": 14
  },
  "MIN LVL FD": 15,
  "saving_throws": [
    "WIS"
  ],
  "Skill": [
    "Arcana"
  ],
  "Hidden Ability": "Multiscale"
}