{
  "Moves": {
    "Level": {
      "14": [
        "Brine",
        "Whirlpool"
      ],
      "18": [
        "Mist",
        "Drill Peck",
        "Hydro Pump"
      ]
    },
    "Starting Moves": [
      "Aqua Jet",
      "Bubble",
      "Growl",
      "Metal Claw",
      "Tackle",
      "Swords Dance",
      "Peck",
      "Bubble Beam",
      "Swagger",
      "Fury Attack"
    ],
    "TM": [
      1,
      5,
      6,
      7,
      10,
      13,
      14,
      15,
      17,
      18,
      21,
      26,
      27,
      31,
      32,
      39,
      40,
      42,
      44,
      45,
      48,
      49,
      51,
      55,
      56,
      60,
      65,
      68,
      75,
      78,
      80,
      86,
      87,
      88,
      90,
      91,
      94,
      98,
      100
    ]
  },
  "index": 395,
  "Abilities": [
    "Torrent"
  ],
  "Type": [
    "Water",
    "Steel"
  ],
  "SR": 13.0,
  "AC": 16,
  "Hit Dice": 12,
  "HP": 117,
  "WSp": 30,
  "Ssp": 50,
  "attributes": {
    "STR": 17,
    "DEX": 15,
    "CON": 18,
    "INT": 6,
    "WIS": 14,
    "CHA": 10
  },
  "MIN LVL FD": 10,
  "saving_throws": [
    "CON",
    "STR"
  ],
  "Skill": [
    "Survival",
    "Intimidation"
  ],
  "Hidden Ability": "Defiant"
}