{
  "Moves": {
    "Level": {
      "2": [
        "Water Gun",
        "Attract",
        "Rain Dance"
      ],
      "6": [
        "Gust",
        "Water Pulse"
      ],
      "10": [
        "Captivate",
        "Safeguard"
      ],
      "14": [
        "Aqua Ring",
        "Whirlpool"
      ],
      "18": [
        "U-Turn",
        "Bounce",
        "Silver Wind",
        "Soak"
      ]
    },
    "Starting Moves": [
      "Pound"
    ],
    "TM": [
      6,
      7,
      10,
      13,
      14,
      17,
      18,
      20,
      21,
      27,
      32,
      42,
      44,
      45,
      48,
      55,
      66,
      77,
      87,
      88,
      89,
      90,
      94,
      96,
      98,
      100
    ]
  },
  "index": 456,
  "Abilities": [
    "Swift Swim",
    "Storm Drain"
  ],
  "Type": [
    "Water"
  ],
  "SR": 2.0,
  "AC": 14,
  "Hit Dice": 6,
  "HP": 17,
  "WSp": 5,
  "Ssp": 25,
  "Senses": [
    "Darkvision 30ft"
  ],
  "attributes": {
    "STR": 11,
    "DEX": 14,
    "CON": 13,
    "INT": 6,
    "WIS": 12,
    "CHA": 10
  },
  "MIN LVL FD": 1,
  "Evolve": "Lumineon",
  "saving_throws": [
    "DEX"
  ],
  "Skill": [
    "Nature",
    "Perception"
  ],
  "Hidden Ability": "Water Veil"
}