{
  "Moves": {
    "Level": {
      "6": [
        "Flail",
        "Roost"
      ],
      "10": [
        "Razor Wind",
        "Natural Gift"
      ],
      "14": [
        "Flame Charge",
        "Acrobatics",
        "Me First"
      ],
      "18": [
        "Tailwind",
        "Steel Wing"
      ]
    },
    "Starting Moves": [
      "Ember",
      "Tackle",
      "Growl",
      "Quick Attack",
      "Peck",
      "Agility"
    ],
    "TM": [
      1,
      6,
      10,
      11,
      12,
      17,
      19,
      21,
      27,
      32,
      35,
      38,
      40,
      42,
      43,
      44,
      45,
      46,
      48,
      50,
      51,
      61,
      62,
      75,
      76,
      87,
      88,
      89,
      90,
      100
    ]
  },
  "index": 662,
  "Abilities": [
    "Flame Body"
  ],
  "Type": [
    "Fire",
    "Flying"
  ],
  "SR": 6.0,
  "AC": 14,
  "Hit Dice": 8,
  "HP": 52,
  "WSp": 20,
  "Fsp": 30,
  "attributes": {
    "STR": 12,
    "DEX": 16,
    "CON": 14,
    "INT": 6,
    "WIS": 12,
    "CHA": 10
  },
  "MIN LVL FD": 5,
  "Evolve": "Talonflame",
  "saving_throws": [
    "DEX"
  ],
  "Skill": [
    "Perception"
  ],
  "Hidden Ability": "Gale Wings"
}