{
  "Moves": {
    "Level": {
      "2": [
        "Absorb",
        "Night Shade",
        "Bubble Beam"
      ],
      "6": [
        "Recover",
        "Water Pulse"
      ],
      "10": [
        "Ominous Wind",
        "Brine"
      ],
      "14": [
        "Rain Dance",
        "Hex"
      ],
      "18": [
        "Hydro Pump",
        "Wring Out",
        "Water Spout"
      ]
    },
    "Starting Moves": [
      "Bubble",
      "Water Sport"
    ],
    "TM": [
      6,
      7,
      10,
      12,
      13,
      14,
      17,
      18,
      20,
      21,
      27,
      29,
      30,
      32,
      34,
      36,
      42,
      44,
      45,
      48,
      53,
      55,
      61,
      77,
      85,
      87,
      88,
      90,
      92,
      94,
      97,
      98,
      99,
      100
    ]
  },
  "index": 592,
  "Abilities": [
    "Water Absorb",
    "Cursed Body"
  ],
  "Type": [
    "Water",
    "Ghost"
  ],
  "SR": 2.0,
  "AC": 14,
  "Hit Dice": 6,
  "HP": 17,
  "Ssp": 25,
  "Fsp": 25,
  "Senses": [
    "Darkvision 30ft"
  ],
  "attributes": {
    "STR": 14,
    "DEX": 11,
    "CON": 13,
    "INT": 6,
    "WIS": 13,
    "CHA": 10
  },
  "MIN LVL FD": 1,
  "Evolve": "Jellicent",
  "saving_throws": [
    "WIS"
  ],
  "Skill": [
    "Deception"
  ],
  "Hidden Ability": "Damp"
}