{
  "AC": 16,
  "Abilities": [
    "Torrent"
  ],
  "HP": 117,
  "Hidden Ability": "Protean",
  "Hit Dice": 12,
  "MIN LVL FD": 10,
  "Moves": {
    "Level": {
      "14": [
        "Feint Attack",
        "Substitute",
        "Extrasensory"
      ],
      "18": [
        "Double Team",
        "Hydro Pump",
        "Night Slash",
        "Haze"
      ]
    },
    "Starting Moves": [
      "Water Shuriken",
      "Role Play",
      "Mat Block",
      "Pound",
      "Growl",
      "Bubble",
      "Quick Attack",
      "Lick",
      "Water Pulse",
      "Smokescreen",
      "Shadow Sneak",
      "Spikes"
    ],
    "TM": [
      1,
      6,
      10,
      12,
      13,
      14,
      15,
      17,
      18,
      21,
      23,
      27,
      32,
      39,
      40,
      42,
      44,
      45,
      46,
      48,
      49,
      55,
      56,
      59,
      62,
      68,
      80,
      86,
      87,
      88,
      89,
      90,
      94,
      97,
      98,
      100
    ]
  },
  "SR": 13.0,
  "Skill": [
    "Stealth",
    "Acrobatics"
  ],
  "Ssp": 40,
  "Type": [
    "Water",
    "Dark"
  ],
  "WSp": 40,
  "attributes": {
    "CHA": 10,
    "CON": 16,
    "DEX": 19,
    "INT": 6,
    "STR": 15,
    "WIS": 14
  },
  "index": 658,
  "saving_throws": [
    "Dexterity"
  ],
  "size": "Medium"
}