{
  "Moves": {
    "Level": {
      "2": [
        "Meditate",
        "Detect",
        "Fake Out"
      ],
      "6": [
        "Double Slap",
        "Swift",
        "Calm Mind"
      ],
      "10": [
        "Force Palm",
        "Drain Punch",
        "Jump Kick"
      ],
      "14": [
        "U-Turn",
        "Quick Guard",
        "Bounce"
      ],
      "18": [
        "High Jump Kick",
        "Reversal",
        "Aura Sphere"
      ]
    },
    "Starting Moves": [
      "Pound"
    ],
    "TM": [
      1,
      4,
      6,
      8,
      10,
      11,
      12,
      17,
      18,
      21,
      27,
      31,
      32,
      33,
      39,
      40,
      42,
      44,
      45,
      47,
      48,
      52,
      56,
      62,
      66,
      71,
      75,
      77,
      80,
      84,
      86,
      87,
      88,
      89,
      90,
      100
    ]
  },
  "index": 619,
  "Abilities": [
    "Inner Focus",
    "Regenerator"
  ],
  "Type": [
    "Fighting"
  ],
  "SR": 0.5,
  "AC": 13,
  "Hit Dice": 6,
  "HP": 16,
  "WSp": 30,
  "attributes": {
    "STR": 14,
    "DEX": 13,
    "CON": 11,
    "INT": 6,
    "WIS": 10,
    "CHA": 10
  },
  "MIN LVL FD": 1,
  "Evolve": "Mienshao",
  "saving_throws": [
    "DEX"
  ],
  "Skill": [
    "Athletics",
    "Acrobatics"
  ],
  "Hidden Ability": "Reckless"
}