{
  "AC": 13,
  "Abilities": [
    "Pickup"
  ],
  "Evolve": "Donphan",
  "HP": 17,
  "Hidden Ability": "Sand Veil",
  "Hit Dice": 6,
  "MIN LVL FD": 1,
  "Moves": {
    "Level": {
      "10": [
        "Slam",
        "Take Down"
      ],
      "14": [
        "Charm",
        "Last Resort"
      ],
      "18": [
        "Double-Edge"
      ],
      "2": [
        "Flail",
        "Rollout"
      ],
      "6": [
        "Natural Gift",
        "Endure"
      ]
    },
    "Starting Moves": [
      "Defense Curl",
      "Growl",
      "Odor Sleuth",
      "Tackle"
    ],
    "TM": [
      5,
      6,
      10,
      11,
      17,
      21,
      26,
      27,
      32,
      37,
      39,
      42,
      44,
      45,
      48,
      49,
      78,
      80,
      87,
      88,
      90,
      100
    ],
    "egg": [
      "Ancient Power",
      "Body Slam",
      "Counter",
      "Endeavor",
      "Fissure",
      "Focus Energy",
      "Head Smash",
      "Slam",
      "Ice Shard",
      "Mud-Slap",
      "Play Rough",
      "Snore"
    ]
  },
  "SR": 0.5,
  "Skill": [
    "Athletics",
    "Survival"
  ],
  "Type": [
    "Ground"
  ],
  "WSp": 20,
  "attributes": {
    "CHA": 12,
    "CON": 12,
    "DEX": 10,
    "INT": 6,
    "STR": 13,
    "WIS": 10
  },
  "index": 231,
  "saving_throws": [
    "Strength"
  ],
  "size": "Tiny"
}