{
  "AC": 13,
  "Abilities": [
    "Torrent"
  ],
  "Evolve": "Prinplup",
  "HP": 17,
  "Hidden Ability": "Defiant",
  "Hit Dice": 6,
  "MIN LVL FD": 1,
  "Moves": {
    "Level": {
      "10": [
        "Fury Attack",
        "Brine",
        "Whirlpool"
      ],
      "14": [
        "Mist",
        "Drill Peck"
      ],
      "18": [
        "Hydro Pump"
      ],
      "2": [
        "Bubble",
        "Water Sport"
      ],
      "6": [
        "Peck",
        "Bubble Beam",
        "Bide"
      ]
    },
    "Starting Moves": [
      "Pound",
      "Growl"
    ],
    "TM": [
      1,
      6,
      7,
      10,
      13,
      14,
      17,
      18,
      21,
      27,
      31,
      32,
      39,
      40,
      42,
      44,
      45,
      48,
      49,
      55,
      56,
      60,
      86,
      87,
      88,
      90,
      94,
      98,
      100
    ],
    "egg": [
      "Agility",
      "Aqua Ring",
      "Bide",
      "Double Hit",
      "Flail",
      "Hydro Pump",
      "Mud Sport",
      "Mud-Slap",
      "Snore",
      "Supersonic",
      "Yawn"
    ]
  },
  "SR": 0.5,
  "Skill": [
    "Survival"
  ],
  "Ssp": 30,
  "Type": [
    "Water"
  ],
  "WSp": 25,
  "attributes": {
    "CHA": 10,
    "CON": 13,
    "DEX": 12,
    "INT": 6,
    "STR": 12,
    "WIS": 10
  },
  "index": 393,
  "saving_throws": [
    "Constitution"
  ],
  "size": "Tiny"
}