{
  "Moves": {
    "Level": {},
    "Starting Moves": [
      "Quick Attack",
      "Tail Whip",
      "Thunder Shock",
      "Thunderbolt"
    ],
    "TM": [
      6,
      10,
      15,
      16,
      17,
      19,
      21,
      24,
      25,
      27,
      31,
      32,
      42,
      44,
      45,
      46,
      48,
      52,
      56,
      57,
      68,
      72,
      73,
      86,
      87,
      88,
      90,
      93,
      100
    ]
  },
  "index": 26,
  "Abilities": [
    "Static"
  ],
  "Type": [
    "Electric"
  ],
  "SR": 7.0,
  "AC": 15,
  "Hit Dice": 10,
  "HP": 50,
  "WSp": 30,
  "attributes": {
    "STR": 12,
    "DEX": 18,
    "CON": 15,
    "INT": 6,
    "WIS": 12,
    "CHA": 10
  },
  "MIN LVL FD": 5,
  "saving_throws": [
    "DEX"
  ],
  "Skill": [
    "Acrobatics"
  ],
  "Hidden Ability": "Lightning Rod"
}