{
  "Moves": {
    "Level": {
      "2": [
        "Fury Attack",
        "Scary Face"
      ],
      "6": [
        "Smack Down",
        "Stomp"
      ],
      "10": [
        "Bulldoze",
        "Chip Away",
        "Head Smash"
      ],
      "14": [
        "Rock Blast",
        "Drill Run",
        "Take Down",
        "Stone Edge"
      ],
      "18": [
        "Earthquake",
        "Megahorn",
        "Horn Drill",
        "Double-Edge"
      ]
    },
    "Starting Moves": [
      "Horn Attack",
      "Tail Whip"
    ],
    "TM": [
      5,
      6,
      10,
      11,
      13,
      14,
      17,
      18,
      21,
      23,
      24,
      25,
      26,
      27,
      32,
      35,
      37,
      38,
      39,
      42,
      44,
      45,
      46,
      48,
      66,
      67,
      69,
      71,
      75,
      78,
      80,
      84,
      87,
      88,
      90,
      100
    ]
  },
  "index": 111,
  "Abilities": [
    "Lightning Rod",
    "Rock Head"
  ],
  "Type": [
    "Ground",
    "Rock"
  ],
  "SR": 3.0,
  "AC": 13,
  "Hit Dice": 8,
  "HP": 45,
  "WSp": 30,
  "Senses": [
    "Tremorsense 40ft"
  ],
  "attributes": {
    "STR": 15,
    "DEX": 10,
    "CON": 14,
    "INT": 6,
    "WIS": 10,
    "CHA": 10
  },
  "MIN LVL FD": 1,
  "Evolve": "Rhydon",
  "saving_throws": [
    "STR",
    "CON"
  ],
  "Skill": [
    "Athletics"
  ],
  "Hidden Ability": "Reckless"
}