{
  "AC": 13,
  "Abilities": [
    "Overgrow"
  ],
  "Evolve": "Dartrix",
  "Fsp": 25,
  "HP": 18,
  "Hidden Ability": "Long Reach",
  "Hit Dice": 6,
  "MIN LVL FD": 1,
  "Moves": {
    "Level": {
      "10": [
        "Synthesis",
        "Fury Attack",
        "Sucker Punch"
      ],
      "14": [
        "Leaf Blade",
        "Feather Dance"
      ],
      "18": [
        "Brave Bird",
        "Nasty Plot"
      ],
      "2": [
        "Peck",
        "Astonish"
      ],
      "6": [
        "Razor Leaf",
        "Ominous Wind",
        "Foresight",
        "Pluck"
      ]
    },
    "Starting Moves": [
      "Leafage",
      "Tackle",
      "Growl"
    ],
    "TM": [
      1,
      6,
      10,
      11,
      16,
      17,
      19,
      20,
      21,
      22,
      27,
      32,
      42,
      44,
      45,
      48,
      49,
      51,
      53,
      54,
      65,
      75,
      86,
      87,
      88,
      90,
      96,
      100
    ],
    "egg": [
      "Baton Pass",
      "Confuse Ray",
      "Curse",
      "Defog",
      "Haze",
      "Ominous Wind"
    ]
  },
  "SR": 0.5,
  "Senses": [
    "Darkvision 30ft"
  ],
  "Skill": [
    "Acrobatics"
  ],
  "Type": [
    "Grass",
    "Flying"
  ],
  "WSp": 5,
  "attributes": {
    "CHA": 10,
    "CON": 14,
    "DEX": 13,
    "INT": 6,
    "STR": 10,
    "WIS": 10
  },
  "index": 722,
  "saving_throws": [
    "Dexterity"
  ],
  "size": "Tiny"
}