{
  "AC": 14,
  "Abilities": [
    "Thick Fat",
    "Hydration"
  ],
  "Evolve": "Dewgong",
  "HP": 17,
  "Hidden Ability": "Ice Body",
  "Hit Dice": 6,
  "MIN LVL FD": 1,
  "Moves": {
    "Level": {
      "10": [
        "Aqua Ring",
        "Aurora Beam"
      ],
      "14": [
        "Aqua Jet",
        "Brine",
        "Take Down",
        "Dive"
      ],
      "18": [
        "Aqua Tail",
        "Ice Beam",
        "Safeguard",
        "Hail"
      ],
      "2": [
        "Water Sport",
        "Icy Wind"
      ],
      "6": [
        "Encore",
        "Ice Shard",
        "Rest"
      ]
    },
    "Starting Moves": [
      "Headbutt",
      "Growl"
    ],
    "TM": [
      6,
      7,
      10,
      13,
      14,
      17,
      18,
      20,
      21,
      27,
      32,
      42,
      44,
      45,
      46,
      48,
      49,
      56,
      67,
      87,
      88,
      90,
      94,
      98,
      100
    ],
    "egg": [
      "Belch",
      "Disable",
      "Encore",
      "Entrainment",
      "Fake Out",
      "Horn Drill",
      "Icicle Spear",
      "Lick",
      "Perish Song",
      "Signal Beam",
      "Slam",
      "Sleep Talk",
      "Spit Up",
      "Stockpile",
      "Swallow",
      "Water Pulse"
    ]
  },
  "SR": 0.5,
  "Skill": [
    "Acrobatics"
  ],
  "Ssp": 30,
  "Type": [
    "Water"
  ],
  "WSp": 10,
  "attributes": {
    "CHA": 10,
    "CON": 12,
    "DEX": 11,
    "INT": 6,
    "STR": 13,
    "WIS": 10
  },
  "index": 86,
  "saving_throws": [
    "Dexterity"
  ],
  "size": "Small"
}