{
  "AC": 13,
  "Abilities": [
    "Torrent"
  ],
  "Evolve": "Croconaw",
  "HP": 17,
  "Hidden Ability": "Sheer Force",
  "Hit Dice": 6,
  "MIN LVL FD": 1,
  "Moves": {
    "Level": {
      "10": [
        "Crunch",
        "Chip Away"
      ],
      "14": [
        "Slash",
        "Screech",
        "Thrash"
      ],
      "18": [
        "Aqua Tail",
        "Superpower",
        "Hydro Pump"
      ],
      "2": [
        "Water Gun",
        "Rage",
        "Bite"
      ],
      "6": [
        "Scary Face",
        "Ice Fang",
        "Flail"
      ]
    },
    "Starting Moves": [
      "Leer",
      "Scratch"
    ],
    "TM": [
      1,
      2,
      6,
      7,
      10,
      13,
      14,
      17,
      18,
      21,
      27,
      31,
      32,
      39,
      40,
      42,
      44,
      45,
      48,
      55,
      56,
      65,
      75,
      80,
      87,
      88,
      90,
      94,
      98,
      100
    ],
    "egg": [
      "Ancient Power",
      "Crunch",
      "Dragon Claw",
      "Dragon Dance",
      "Flatter",
      "Hydro Pump",
      "Ice Punch",
      "Metal Claw",
      "Mud Sport",
      "Rock Slide",
      "Thrash",
      "Water Sport"
    ]
  },
  "SR": 0.5,
  "Skill": [
    "Athletics"
  ],
  "Ssp": 20,
  "Type": [
    "Water"
  ],
  "WSp": 30,
  "attributes": {
    "CHA": 10,
    "CON": 13,
    "DEX": 11,
    "INT": 6,
    "STR": 13,
    "WIS": 10
  },
  "index": 158,
  "saving_throws": [
    "Strength"
  ],
  "size": "Tiny"
}