{
  "Moves": {
    "Level": {},
    "Starting Moves": [
      "Defense Curl",
      "Disable",
      "Double-Edge",
      "Double Slap",
      "Play Rough",
      "Sing"
    ],
    "TM": [
      1,
      6,
      10,
      11,
      13,
      14,
      15,
      16,
      17,
      18,
      20,
      21,
      22,
      24,
      25,
      27,
      29,
      30,
      31,
      32,
      33,
      35,
      38,
      42,
      44,
      45,
      48,
      49,
      52,
      56,
      57,
      68,
      73,
      74,
      77,
      85,
      86,
      87,
      88,
      90,
      93,
      99,
      100
    ]
  },
  "index": 40,
  "Abilities": [
    "Cute Charm",
    "Competitive"
  ],
  "Type": [
    "Normal",
    "Fairy"
  ],
  "SR": 6.0,
  "AC": 15,
  "Hit Dice": 10,
  "HP": 56,
  "WSp": 30,
  "attributes": {
    "STR": 14,
    "DEX": 13,
    "CON": 14,
    "INT": 6,
    "WIS": 14,
    "CHA": 14
  },
  "MIN LVL FD": 5,
  "saving_throws": [
    "WIS",
    "CHA"
  ],
  "Skill": [
    "Insight",
    "Persuasion"
  ],
  "Hidden Ability": "Frisk"
}