{
  "AC": 13,
  "Abilities": [
    "Shadow Tag"
  ],
  "HP": 80,
  "Hidden Ability": "Telepathy",
  "Hit Dice": 12,
  "MIN LVL FD": 5,
  "Moves": {
    "Level": {},
    "Starting Moves": [
      "Counter",
      "Destiny Bond",
      "Mirror Coat",
      "Safeguard"
    ],
    "TM": [
      20
    ]
  },
  "SR": 6.0,
  "Senses": [
    "Darkvision 40ft"
  ],
  "Skill": [
    "Survival"
  ],
  "Type": [
    "Psychic"
  ],
  "WSp": 30,
  "attributes": {
    "CHA": 10,
    "CON": 20,
    "DEX": 9,
    "INT": 6,
    "STR": 13,
    "WIS": 14
  },
  "index": 202,
  "saving_throws": [
    "Wisdom",
    "Constitution"
  ],
  "size": "Medium"
}