{
  "Damage": {
    "1": {
      "amount": 2,
      "dice_max": 10,
      "move": true
    },
    "10": {
      "amount": 4,
      "dice_max": 10,
      "move": true
    },
    "17": {
      "amount": 7,
      "dice_max": 8,
      "move": true
    },
    "5": {
      "amount": 3,
      "dice_max": 8,
      "move": true
    }
  },
  "Description": "You charge an opponent for a devastating horn attack. Make a melee attack roll, doing bug damage on a hit. If the user moves at least 20 feet towards a target before using this move, the target is forced to make a STR save against your Move DC or be knocked prone.",
  "Duration": "Instantaneous",
  "Move Power": [
    "STR",
    "DEX"
  ],
  "Move Time": "1 action",
  "PP": 5,
  "Range": "Melee",
  "Save": "STR",
  "Type": "Bug",
  "atk": true
}