{
  "Damage": {
    "1": {
      "amount": 2,
      "dice_max": 6,
      "move": true
    },
    "10": {
      "amount": 6,
      "dice_max": 6,
      "move": true
    },
    "17": {
      "amount": 7,
      "dice_max": 8,
      "move": true
    },
    "5": {
      "amount": 3,
      "dice_max": 8,
      "move": true
    }
  },
  "Description": "Your body glows a bright and brilliant blue, sending three beams of focused light at any creature(s) in range. Make a ranged attack for each beam, dealing water damage on each successful hit.",
  "Duration": "Instantaneous",
  "Move Power": [
    "STR",
    "DEX"
  ],
  "Move Time": "1 action",
  "PP": 5,
  "Range": "100ft",
  "Type": "Water",
  "atk": true
}