{
  "Description": "You quickly fire a sticky web at a creature entering the battle. When a creature is switched into battle, you may use your reaction to make a ranged attack on the creature. On a hit, the target is restrained. The creature may make a STR save against your Move DC at the beginning of each of its turns to escape the web.",
  "Duration": "Instantaneous",
  "Move Power": [
    "DEX"
  ],
  "Move Time": "1 reaction",
  "PP": 3,
  "Range": "50ft",
  "Save": "STR",
  "Type": "Bug",
  "atk": true
}