{
  "Damage": {
    "1": {
      "amount": 4,
      "dice_max": 6,
      "move": true
    },
    "10": {
      "amount": 6,
      "dice_max": 8,
      "move": true
    },
    "17": {
      "amount": 6,
      "dice_max": 12,
      "move": true
    },
    "5": {
      "amount": 5,
      "dice_max": 6,
      "move": true
    }
  },
  "Description": "You strike a target with incredible power - but with great power comes great responsibility. Make a melee attack against a creature, dealing fighting damage on a hit. This move exhausts you, and your STR and DEX ability scores are set to 10 while you remain in battle.",
  "Duration": "Instantaneous",
  "Move Power": [
    "STR",
    "DEX"
  ],
  "Move Time": "1 action",
  "PP": 3,
  "Range": "Melee",
  "Type": "Fighting",
  "atk": true
}