{
  "Damage": {
    "1": {
      "amount": 2,
      "dice_max": 6,
      "move": true
    },
    "10": {
      "amount": 2,
      "dice_max": 8,
      "move": true,
      "times": 2
    },
    "17": {
      "amount": 3,
      "dice_max": 8,
      "move": true,
      "times": 2
    },
    "5": {
      "amount": 2,
      "dice_max": 8,
      "move": true
    }
  },
  "Description": "When you activate this move, a sword appears and dances around you, increasing your AC by 1. As a bonus action on a future turn, you may drop concentration to release this sword and roll a ranged attack at a target within 30 feet of you, dealing normal damage on a hit.",
  "Duration": "1 minute, concentration",
  "Move Power": [
    "DEX",
    "WIS"
  ],
  "Move Time": "1 action",
  "PP": 5,
  "Range": "Self",
  "Type": "Normal",
  "atk": true
}