{
  "Damage": {
    "1": {
      "amount": 1,
      "dice_max": 8,
      "move": true
    },
    "10": {
      "amount": 4,
      "dice_max": 4,
      "move": true
    },
    "17": {
      "amount": 3,
      "dice_max": 10,
      "move": true
    },
    "5": {
      "amount": 2,
      "dice_max": 6,
      "move": true
    }
  },
  "Description": "You send a powerful ball of energy that changes type based on the surrounding weather, dealing damage of that type. |Weather|Type| |:--:|:--: |Harsh Sunlight|Fire |Rain|Water |Sandstorm|Rock |Hail or Snow|Ice |Foggy or Cloudy|Normal",
  "Duration": "Instantaneous",
  "Move Power": [
    "STR",
    "DEX"
  ],
  "Move Time": "1 action",
  "PP": 5,
  "Range": "30ft",
  "Type": "Normal"
}